purplship/mappers/fedex/__init__.py
purplship/mappers/fedex/mapper.py
purplship/mappers/fedex/proxy.py
purplship/mappers/fedex/settings.py
purplship/providers/fedex/__init__.py
purplship/providers/fedex/address.py
purplship/providers/fedex/error.py
purplship/providers/fedex/pickup/__init__.py
purplship/providers/fedex/pickup/availability.py
purplship/providers/fedex/pickup/cancel.py
purplship/providers/fedex/pickup/create.py
purplship/providers/fedex/pickup/update.py
purplship/providers/fedex/rate.py
purplship/providers/fedex/shipment/__init__.py
purplship/providers/fedex/shipment/cancel.py
purplship/providers/fedex/shipment/create.py
purplship/providers/fedex/tracking.py
purplship/providers/fedex/units.py
purplship/providers/fedex/utils.py
purplship.fedex-2022.2.dist-info/WHEEL
purplship.fedex-2022.2.dist-info/METADATA
purplship.fedex-2022.2.dist-info/RECORD
