Metadata-Version: 2.1
Name: purplship.fedex
Version: 2022.2
Summary: Purplship - Fedex Shipping Extension
Home-page: https://next.purplship.com/docs/guides/sdk
License: Apache-2.0
Author: Purplship
Author-email: hello@purplship.com
Requires-Python: >=3.7,<4.0
Classifier: Intended Audience :: Developers
Classifier: License :: OSI Approved :: Apache Software License
Classifier: Operating System :: OS Independent
Classifier: Programming Language :: Python :: 3
Classifier: Programming Language :: Python :: 3.10
Classifier: Programming Language :: Python :: 3.7
Classifier: Programming Language :: Python :: 3.8
Classifier: Programming Language :: Python :: 3.9
Requires-Dist: carrier.fedex
Requires-Dist: purplship
Project-URL: Repository, https://github.com/purplship/purplship
